aphcli/__init__.py
aphcli/compute.py
aphcli/datasets.py
aphcli/describe_utils.py
aphcli/job.py
aphcli/main.py
aphcli/models.py
aphcli/utils.py
aphcli/version.py
aphcli/api/__init__.py
aphcli/api/compute.py
aphcli/api/datasets.py
aphcli/api/job.py
aphcli/api/models.py
aphcli/api/pydantic_models.py
aphcli/api/utils/__init__.py
aphcli/api/utils/comms.py
aphcli/api/utils/compute_spec_formatting.py
aphcli/api/utils/interaction.py
aphcli/api/utils/prettytable_helpers.py
apheris/__init__.py
apheris_cli-0.44.1.data/data/pypi-readme.md
apheris_cli-0.44.1.data/data/requirements.txt
apheris_cli-0.44.1.dist-info/licenses/LICENSE
apheris_cli-0.44.1.dist-info/METADATA
apheris_cli-0.44.1.dist-info/WHEEL
apheris_cli-0.44.1.dist-info/entry_points.txt
apheris_cli-0.44.1.dist-info/top_level.txt
apheris_cli-0.44.1.dist-info/RECORD
