Metadata-Version: 2.4
Name: apheris-cli
Version: 0.44.1
Summary: Apheris CLI package for interaction with the Apheris product.
Author: Apheris
Keywords: python,apheris,federated learning
License-File: LICENSE
Requires-Dist: apheris-auth==0.21.*
Requires-Dist: prettytable==3.16.0
Requires-Dist: typer==0.19.2
Requires-Dist: semver==3.0.4
Requires-Dist: urllib3==2.5.0
Dynamic: author
Dynamic: description
Dynamic: description-content-type
Dynamic: keywords
Dynamic: license-file
Dynamic: requires-dist
Dynamic: summary
